README.txt
TODO.txt
setup.py
collective/__init__.py
collective.proxyproperties.egg-info/PKG-INFO
collective.proxyproperties.egg-info/SOURCES.txt
collective.proxyproperties.egg-info/dependency_links.txt
collective.proxyproperties.egg-info/entry_points.txt
collective.proxyproperties.egg-info/namespace_packages.txt
collective.proxyproperties.egg-info/not-zip-safe
collective.proxyproperties.egg-info/paster_plugins.txt
collective.proxyproperties.egg-info/requires.txt
collective.proxyproperties.egg-info/top_level.txt
collective/proxyproperties/__init__.py
collective/proxyproperties/adapters.py
collective/proxyproperties/configure.zcml
collective/proxyproperties/interfaces.py
collective/proxyproperties/permissions.py
collective/proxyproperties/permissions.zcml
collective/proxyproperties/utility.py
collective/proxyproperties/browser/__init__.py
collective/proxyproperties/browser/configure.zcml
collective/proxyproperties/browser/proxypropsedit.pt
collective/proxyproperties/browser/proxypropsedit.py
collective/proxyproperties/profiles/default/actions.xml
collective/proxyproperties/profiles/default/rolemap.xml
collective/proxyproperties/profiles/uninstall/actions.xml
docs/HISTORY.txt