Metadata-Version: 1.0
Name: collective.proxyproperties
Version: 0.2
Summary: Local utility to set portal properties for a sub site
Home-page: UNKNOWN
Author: Six Feet Up, Inc.
Author-email: info@sixfeetup.com
License: GPL
Keywords: plone
Platform: UNKNOWN
Classifier: Programming Language :: Python
Classifier: Topic :: Software Development :: Libraries :: Python Modules
